pymarc/__init__.py
pymarc/constants.py
pymarc/exceptions.py
pymarc/field.py
pymarc/leader.py
pymarc/marc8.py
pymarc/marc8_mapping.py
pymarc/marcjson.py
pymarc/marcxml.py
pymarc/py.typed
pymarc/reader.py
pymarc/record.py
pymarc/writer.py
pymarc-5.2.3.dist-info/METADATA
pymarc-5.2.3.dist-info/WHEEL
pymarc-5.2.3.dist-info/licenses/LICENSE
pymarc-5.2.3.dist-info/RECORD
