Metadata-Version: 2.3
Name: pymarc
Version: 5.2.3
Summary: Read, write and modify MARC bibliographic data
License: Redistribution and use in source and binary forms, with or without
License-File: LICENSE
Requires-Python: >=3.8
